nestpy/__init__.py
nestpy/_nestpy.cpython-38-x86_64-linux-gnu.so
nestpy/bindings.cpp
nestpy/helpers.py
nestpy-2.0.6.dist-info/METADATA
nestpy-2.0.6.dist-info/WHEEL
nestpy-2.0.6.dist-info/RECORD
nestpy-2.0.6.dist-info/licenses/AUTHORS.md
nestpy-2.0.6.dist-info/licenses/LICENSE
