Metadata-Version: 2.2
Name: nestpy
Version: 2.0.6
Summary: Python bindings for the NEST noble element simulation
Author-Email: Sam Eriksen <sam.eriksen@bristol.ac.uk>, Greg Rischbieter <rischbie@umich.edu>, Nicholas Carrara <ncarrara.physics@gmail.com>, Sophia Andaloro <sja5@rice.edu>, Christopher Tunnell <tunnell@rice.edu>
License:                     GNU GENERAL PUBLIC LICENSE
Classifier: Development Status :: 5 - Production/Stable
Classifier: License :: OSI Approved :: GNU General Public License v3 (GPLv3)
Classifier: Natural Language :: English
Classifier: Programming Language :: Python :: 3.8
Classifier: Programming Language :: Python :: 3.9
Classifier: Programming Language :: Python :: 3.10
Classifier: Programming Language :: Python :: 3.11
Classifier: Programming Language :: C++
Classifier: Intended Audience :: Science/Research
Classifier: Programming Language :: Python :: Implementation :: CPython
Classifier: Topic :: Scientific/Engineering :: Physics
Classifier: Operating System :: MacOS :: MacOS X
Classifier: Operating System :: POSIX :: Linux
Requires-Dist: numpy
